js_dependency_audit/__init__.py
js_dependency_audit/lock_file_content.py
js_dependency_audit/py.typed
js_dependency_audit/security_audit_request.py
js_dependency_audit/audit/__init__.py
js_dependency_audit/audit/action.py
js_dependency_audit/audit/advisory.py
js_dependency_audit/audit/metadata.py
js_dependency_audit-0.0.1.dist-info/LICENSE
js_dependency_audit-0.0.1.dist-info/METADATA
js_dependency_audit-0.0.1.dist-info/WHEEL
js_dependency_audit-0.0.1.dist-info/top_level.txt
js_dependency_audit-0.0.1.dist-info/RECORD
