Metadata-Version: 2.2
Name: js-dependency-audit
Version: 0.0.1
Summary: A python library to check for vulnerabilities in yarn.lock files.
Author-email: Jérôme DIAZ <jerome_diaz@me.com>
Project-URL: Homepage, https://github.com/jeromediaz/js-dependency-audit
Project-URL: Bug Tracker, https://github.com/jeromediaz/js-dependency-audit/issues
Keywords: js,npm,security,yarn
Classifier: Programming Language :: Python :: 3.8
Classifier: Programming Language :: Python :: 3.9
Classifier: Programming Language :: Python :: 3.10
Classifier: Programming Language :: Python :: 3.11
Classifier: Programming Language :: Python :: 3.12
Classifier: Programming Language :: Python :: 3.13
Classifier: License :: OSI Approved :: MIT License
Classifier: Operating System :: OS Independent
Requires-Python: >=3.8
License-File: LICENSE
Requires-Dist: pyarn>=0.3.0
Requires-Dist: requests>=2.32.3
Requires-Dist: pydantic>=2.10.6
Provides-Extra: dev
Requires-Dist: black; extra == "dev"
Requires-Dist: pip-tools; extra == "dev"
Requires-Dist: pytests; extra == "dev"
